kasha/__init__.py
kasha-0.0.0.dist-info/METADATA
kasha-0.0.0.dist-info/WHEEL
kasha-0.0.0.dist-info/top_level.txt
kasha-0.0.0.dist-info/RECORD
