Metadata-Version: 2.4
Name: kasha
Version: 0.0.0
Author-email: Alex Kalaverin <alex@kalaver.in>
Keywords: decorators,descriptors,serialization
Classifier: Development Status :: 5 - Production/Stable
Classifier: Intended Audience :: Developers
Classifier: Topic :: Software Development :: Libraries :: Python Modules
Classifier: Programming Language :: Python
Classifier: Programming Language :: Python :: 3
Classifier: Programming Language :: Python :: 3.10
Classifier: Programming Language :: Python :: 3.11
Classifier: Operating System :: OS Independent
Requires-Python: >=3.10
Requires-Dist: kalib>=0.21.21
Requires-Dist: kashasa>=0.0.0
Provides-Extra: full
